LICENSE
LICENSE.txt
README.md
setup.py
pyzkc.egg-info/PKG-INFO
pyzkc.egg-info/SOURCES.txt
pyzkc.egg-info/dependency_links.txt
pyzkc.egg-info/not-zip-safe
pyzkc.egg-info/top_level.txt
zk/__init__.py
zk/attendance.py
zk/base.py
zk/const.py
zk/exception.py
zk/finger.py
zk/user.py