Metadata-Version: 2.1
Name: pyzkc
Version: 0.9.1
Summary: an unofficial library of zksoftware fingerprint device
Home-page: https://github.com/fananimi/pyzk
Author: Fanani M. Ihsan
Author-email: fanani.mi@gmail.com
License: LICENSE.txt
Keywords: zk,pyzk,zksoftware,attendance machine,fingerprint,biometrics,security
Platform: UNKNOWN
License-File: LICENSE
License-File: LICENSE.txt
